abu/_2fa.py
abu/__init__.py
abu/crypto.py
abu/notify.py
abu/text.py
abu/tools.py
abu/utils.py
py_abu-1.3.7.dist-info/METADATA
py_abu-1.3.7.dist-info/WHEEL
py_abu-1.3.7.dist-info/top_level.txt
py_abu-1.3.7.dist-info/RECORD
