Metadata-Version: 2.4
Name: py-abu
Version: 1.3.7
Summary: Abu API - Personal utility toolkit
Author-email: Chris <10512@qq.com>
License: MIT
Project-URL: Homepage, https://github.com/ChrisYP/abu
Project-URL: Repository, https://github.com/ChrisYP/abu
Keywords: abu,utility,toolkit,crypto,notify
Classifier: Development Status :: 4 - Beta
Classifier: Intended Audience :: Developers
Classifier: License :: OSI Approved :: MIT License
Classifier: Programming Language :: Python :: 3
Classifier: Programming Language :: Python :: 3.8
Classifier: Programming Language :: Python :: 3.9
Classifier: Programming Language :: Python :: 3.10
Classifier: Programming Language :: Python :: 3.11
Classifier: Programming Language :: Python :: 3.12
Requires-Python: >=3.8
Requires-Dist: loguru>=0.7.0
Requires-Dist: pyperclip>=1.8.0
Requires-Dist: curl_cffi>=0.5.0
Requires-Dist: Brotli>=1.0.0
Requires-Dist: msoffcrypto-tool>=5.0.0
Requires-Dist: pandas>=2.0.0
Requires-Dist: openpyxl>=3.1.0
Requires-Dist: cryptography>=41.0.0
